catanatron_gym/__init__.py
catanatron_gym/board_tensor_features.py
catanatron_gym/features.py
catanatron_gym/envs/__init__.py
catanatron_gym/envs/catanatron_env.py
catanatron_gym-4.0.0.dist-info/METADATA
catanatron_gym-4.0.0.dist-info/WHEEL
catanatron_gym-4.0.0.dist-info/top_level.txt
catanatron_gym-4.0.0.dist-info/RECORD
