Metadata-Version: 2.1
Name: catanatron-gym
Version: 4.0.0
Summary: Open AI Gym to play 1v1 Catan against a random bot
Home-page: https://github.com/bcollazo/catanatron
Author: Bryan Collazo
Author-email: bcollazo2010@gmail.com
Classifier: Programming Language :: Python :: 3
Classifier: License :: OSI Approved :: MIT License
Classifier: Operating System :: OS Independent
Requires-Python: >=3.6
Requires-Dist: catanatron
Requires-Dist: gymnasium ==0.29.1
Requires-Dist: numpy
